odoo9_addon_website_portal_contact-9.0.1.0.0-py2.7-nspkg.pth
odoo_addons/website_portal_contact/__openerp__.py
odoo_addons/website_portal_contact/__init__.py
odoo_addons/website_portal_contact/README.rst
odoo_addons/website_portal_contact/security/ir.rule.csv
odoo_addons/website_portal_contact/security/ir.model.access.csv
odoo_addons/website_portal_contact/i18n/es.po
odoo_addons/website_portal_contact/views/layout.xml
odoo_addons/website_portal_contact/views/assets.xml
odoo_addons/website_portal_contact/views/contact_tree.xml
odoo_addons/website_portal_contact/views/contact_form.xml
odoo_addons/website_portal_contact/controllers/main.py
odoo_addons/website_portal_contact/controllers/__init__.py
odoo_addons/website_portal_contact/tests/__init__.py
odoo_addons/website_portal_contact/tests/test_ui.py
odoo_addons/website_portal_contact/static/description/icon.png
odoo_addons/website_portal_contact/static/src/js/portal_contact.tour.js
odoo9_addon_website_portal_contact-9.0.1.0.0.dist-info/top_level.txt
odoo9_addon_website_portal_contact-9.0.1.0.0.dist-info/WHEEL
odoo9_addon_website_portal_contact-9.0.1.0.0.dist-info/RECORD
odoo9_addon_website_portal_contact-9.0.1.0.0.dist-info/metadata.json
odoo9_addon_website_portal_contact-9.0.1.0.0.dist-info/DESCRIPTION.rst
odoo9_addon_website_portal_contact-9.0.1.0.0.dist-info/METADATA
odoo9_addon_website_portal_contact-9.0.1.0.0.dist-info/namespace_packages.txt
