Metadata-Version: 2.0
Name: odoo9-addon-website-portal-contact
Version: 9.0.1.0.0
Summary: Allows logged in portal users to manage their contacts
Home-page: https://tecnativa.com/
Author: UNKNOWN
Author-email: UNKNOWN
License: LGPL-3
Platform: UNKNOWN
Requires-Dist: odoo (<9.1a,>=9.0a)
Requires-Dist: odoo9-addon-website-portal-v10
Classifier: Programming Language :: Python :: 2.7
Classifier: Framework :: Odoo
Classifier: License :: OSI Approved :: GNU Lesser General Public License v3 (LGPLv3)
